interest/VERSION
interest/__init__.py
interest/adapter.py
interest/backend.py
interest/endpoint.py
interest/middleware.py
interest/provider.py
interest/service.py
interest/tester.py
interest/handler/__init__.py
interest/handler/handler.py
interest/handler/record.py
interest/helpers/__init__.py
interest/helpers/chain.py
interest/helpers/config.py
interest/helpers/loop.py
interest/helpers/match.py
interest/helpers/name.py
interest/helpers/order.py
interest/helpers/plugin.py
interest/helpers/port.py
interest/helpers/python.py
interest/helpers/sticker.py
interest/logger/__init__.py
interest/logger/logger.py
interest/plugins/__init__.py
interest/router/__init__.py
interest/router/parser.py
interest/router/pattern.py
interest/router/router.py
interest-0.0.1.dist-info/DESCRIPTION.rst
interest-0.0.1.dist-info/METADATA
interest-0.0.1.dist-info/RECORD
interest-0.0.1.dist-info/WHEEL
interest-0.0.1.dist-info/metadata.json
interest-0.0.1.dist-info/top_level.txt
tests/component/__init__.py
tests/component/test_middleware.py
tests/component/test_service.py
tests/component/handler/__init__.py
tests/component/handler/test_handler.py
tests/component/handler/test_record.py
tests/component/helpers/__init__.py
tests/component/helpers/test_plugin.py
tests/component/logger/__init__.py
tests/component/logger/test_logger.py
tests/component/plugins/__init__.py
tests/component/router/__init__.py
tests/component/router/test_parser.py
tests/component/router/test_pattern.py
tests/integration/__init__.py
tests/system/__init__.py
tests/system/test_advanced.py
