Metadata-Version: 2.0
Name: interest
Version: 0.0.1
Summary: Interest is a event-driven web framework on top of aiohttp/asyncio.
Home-page: https://github.com/inventive-ninja/interest
Author: roll
Author-email: roll@post.agency
License: MIT
Keywords: web framework
Platform: UNKNOWN
Classifier: Development Status :: 4 - Beta
Classifier: Environment :: Web Environment
Classifier: Intended Audience :: Developers
Classifier: License :: OSI Approved :: MIT License
Classifier: Operating System :: OS Independent
Classifier: Programming Language :: Python :: 2
Classifier: Programming Language :: Python :: 2.7
Classifier: Programming Language :: Python :: 3
Classifier: Programming Language :: Python :: 3.3
Classifier: Programming Language :: Python :: 3.4
Classifier: Programming Language :: Python :: 3.5
Classifier: Topic :: Internet :: WWW/HTTP :: Dynamic Content
Classifier: Topic :: Software Development :: Libraries :: Python Modules
Requires-Dist: aiohttp (==0.14)
Provides-Extra: develop
Requires-Dist: pylint; extra == 'develop'
Requires-Dist: tox; extra == 'develop'
